{
  "holidays": [
    {
      "name": "元旦",
      "start": "2021-01-01",
      "end": "2021-01-03"
    },
    {
      "name": "春节",
      "start": "2021-02-11",
      "end": "2021-02-17"
    },
    {
      "name": "清明节",
      "start": "2021-04-03",
      "end": "2021-04-05"
    },
    {
      "name": "劳动节",
      "start": "2021-05-01",
      "end": "2021-05-05"
    },
    {
      "name": "端午节",
      "start": "2021-06-12",
      "end": "2021-06-14"
    },
    {
      "name": "中秋节",
      "start": "2021-09-19",
      "end": "2021-09-21"
    },
    {
      "name": "国庆节",
      "start": "2021-10-01",
      "end": "2021-10-07"
    }
  ],
  "work": [
    {
      "name": "春节调休",
      "date": "2021-02-07"
    },
    {
      "name": "春节调休",
      "date": "2021-02-20"
    },
    {
      "name": "劳动节调休",
      "date": "2021-04-25"
    },
    {
      "name": "劳动节调休",
      "date": "2021-05-08"
    },
    {
      "name": "中秋节调休",
      "date": "2021-09-18"
    },
    {
      "name": "国庆节调休",
      "date": "2021-09-26"
    },
    {
      "name": "国庆节调休",
      "date": "2021-10-09"
    }
  ]
}
